[
  {
    "id": "1",
    "image": "https://i.ibb.co/LCDLd9g/Screenshot-2024-04-18-002511-removebg-preview.png",
    "name": "মোঃ হাবিবুর রহমান",
    "number": "01723929503"
  },
  {
    "id": "2",
    "image": "https://i.ibb.co/3pYBDb5/IMG-8919-removebg-preview.png",
    "name": "মোঃ নজরুল ইসলাস",
    "number": "01721898887"
  },
  {
    "id": "3",
    "image": "https://i.ibb.co/2cbjGPC/Screenshot-2024-04-18-004420-removebg-preview.png",
    "name": "মোঃ এনামুল হক",
    "number": "01727220212"
  },
  {
    "id": "4",
    "image": "https://i.ibb.co/68g6F22/Screenshot-2024-04-18-173059-removebg-preview.png",
    "name": "মোঃ জমিরুল ইসলাম",
    "number": "01717722257"
  },
  {
    "id": "5",
    "image": "https://i.ibb.co/4t6gCgn/Screenshot-2024-04-18-010141-removebg-preview.png",
    "name": "মোঃ আনোয়ার হোসেন",
    "number": "01713783992"
  },
  {
    "id": "6",
    "image": "https://i.ibb.co/cxpky7Y/Screenshot-2024-04-18-010555-removebg-preview.png",
    "name": "অপূর্ব কুমার দাশ",
    "number": "01716008873"
  },
  {
    "id": "7",
    "image": "https://i.ibb.co/GQTS7W2/IMG-2276-removebg-preview.png",
    "name": "মোঃ নূরুল ইসলাম",
    "number": "01718615330"
  },
  {
    "id": "8",
    "image": "https://i.ibb.co/hZdP0wF/Screenshot-2024-04-18-014128-removebg-preview.png",
    "name": "সাঈদা খানম",
    "number": "01727245963"
  },
  {
    "id": "9",
    "image": "https://i.ibb.co/frkKG3b/Screenshot-2024-04-18-015920-removebg-preview.png",
    "name": "ফারহানা করিম",
    "number": "01719131280"
  },
  {
    "id": "10",
    "image": "https://i.ibb.co/XfBbk3k/Screenshot-2024-04-18-014901.png",
    "name": "এস.এম. মারুফুর রহমান",
    "number": "01919175174"
  },
  {
    "id": "11",
    "image": "https://i.ibb.co/gR0dXk6/Screenshot-2024-04-18-015458-removebg-preview.png",
    "name": "মোঃ জবায়দুর রহমান",
    "number": "01718104223"
  },
  {
    "id": "12",
    "image": "https://i.ibb.co/pwXF4CC/Screenshot-2024-04-18-012757.png",
    "name": "মোঃ আবু সুয়বা",
    "number": "01723170010"
  },
  {
    "id": "13",
    "image": "https://i.ibb.co/9hLMkPZ/IMG-2271-removebg-preview-1.png",
    "name": "মোহাম্মদ ইলিয়াস",
    "number": "01719829068"
  }
]